{
 "base": "gloves_str_dex_int",
 "token": "gloves_str_dex_int",
 "count": 247,
 "weights_source": "pob_real",
 "weights_note": "Complete per-base mod pool + real spawn weights from Path of Building (ModItem.lua). Only mods that can roll on this base are included.",
 "mods": [
  {
   "mod_id": "Strength1",
   "affix_type": "Suffix",
   "group": "Strength",
   "level": 1,
   "text": [
    "+(5-8) to Strength"
   ],
   "weight": 1,
   "source": "base"
  },
  {
   "mod_id": "Strength2",
   "affix_type": "Suffix",
   "group": "Strength",
   "level": 11,
   "text": [
    "+(9-12) to Strength"
   ],
   "weight": 1,
   "source": "base"
  },
  {
   "mod_id": "Strength3",
   "affix_type": "Suffix",
   "group": "Strength",
   "level": 22,
   "text": [
    "+(13-16) to Strength"
   ],
   "weight": 1,
   "source": "base"
  },
  {
   "mod_id": "Strength4",
   "affix_type": "Suffix",
   "group": "Strength",
   "level": 33,
   "text": [
    "+(17-20) to Strength"
   ],
   "weight": 1,
   "source": "base"
  },
  {
   "mod_id": "Strength5",
   "affix_type": "Suffix",
   "group": "Strength",
   "level": 44,
   "text": [
    "+(21-24) to Strength"
   ],
   "weight": 1,
   "source": "base"
  },
  {
   "mod_id": "Strength6",
   "affix_type": "Suffix",
   "group": "Strength",
   "level": 55,
   "text": [
    "+(25-27) to Strength"
   ],
   "weight": 1,
   "source": "base"
  },
  {
   "mod_id": "Strength7",
   "affix_type": "Suffix",
   "group": "Strength",
   "level": 66,
   "text": [
    "+(28-30) to Strength"
   ],
   "weight": 1,
   "source": "base"
  },
  {
   "mod_id": "Strength8",
   "affix_type": "Suffix",
   "group": "Strength",
   "level": 74,
   "text": [
    "+(31-33) to Strength"
   ],
   "weight": 1,
   "source": "base"
  },
  {
   "mod_id": "Dexterity1",
   "affix_type": "Suffix",
   "group": "Dexterity",
   "level": 1,
   "text": [
    "+(5-8) to Dexterity"
   ],
   "weight": 1,
   "source": "base"
  },
  {
   "mod_id": "Dexterity2",
   "affix_type": "Suffix",
   "group": "Dexterity",
   "level": 11,
   "text": [
    "+(9-12) to Dexterity"
   ],
   "weight": 1,
   "source": "base"
  },
  {
   "mod_id": "Dexterity3",
   "affix_type": "Suffix",
   "group": "Dexterity",
   "level": 22,
   "text": [
    "+(13-16) to Dexterity"
   ],
   "weight": 1,
   "source": "base"
  },
  {
   "mod_id": "Dexterity4",
   "affix_type": "Suffix",
   "group": "Dexterity",
   "level": 33,
   "text": [
    "+(17-20) to Dexterity"
   ],
   "weight": 1,
   "source": "base"
  },
  {
   "mod_id": "Dexterity5",
   "affix_type": "Suffix",
   "group": "Dexterity",
   "level": 44,
   "text": [
    "+(21-24) to Dexterity"
   ],
   "weight": 1,
   "source": "base"
  },
  {
   "mod_id": "Dexterity6",
   "affix_type": "Suffix",
   "group": "Dexterity",
   "level": 55,
   "text": [
    "+(25-27) to Dexterity"
   ],
   "weight": 1,
   "source": "base"
  },
  {
   "mod_id": "Dexterity7",
   "affix_type": "Suffix",
   "group": "Dexterity",
   "level": 66,
   "text": [
    "+(28-30) to Dexterity"
   ],
   "weight": 1,
   "source": "base"
  },
  {
   "mod_id": "Dexterity8",
   "affix_type": "Suffix",
   "group": "Dexterity",
   "level": 74,
   "text": [
    "+(31-33) to Dexterity"
   ],
   "weight": 1,
   "source": "base"
  },
  {
   "mod_id": "Dexterity9",
   "affix_type": "Suffix",
   "group": "Dexterity",
   "level": 81,
   "text": [
    "+(34-36) to Dexterity"
   ],
   "weight": 1,
   "source": "base"
  },
  {
   "mod_id": "Intelligence1",
   "affix_type": "Suffix",
   "group": "Intelligence",
   "level": 1,
   "text": [
    "+(5-8) to Intelligence"
   ],
   "weight": 1,
   "source": "base"
  },
  {
   "mod_id": "Intelligence2",
   "affix_type": "Suffix",
   "group": "Intelligence",
   "level": 11,
   "text": [
    "+(9-12) to Intelligence"
   ],
   "weight": 1,
   "source": "base"
  },
  {
   "mod_id": "Intelligence3",
   "affix_type": "Suffix",
   "group": "Intelligence",
   "level": 22,
   "text": [
    "+(13-16) to Intelligence"
   ],
   "weight": 1,
   "source": "base"
  },
  {
   "mod_id": "Intelligence4",
   "affix_type": "Suffix",
   "group": "Intelligence",
   "level": 33,
   "text": [
    "+(17-20) to Intelligence"
   ],
   "weight": 1,
   "source": "base"
  },
  {
   "mod_id": "Intelligence5",
   "affix_type": "Suffix",
   "group": "Intelligence",
   "level": 44,
   "text": [
    "+(21-24) to Intelligence"
   ],
   "weight": 1,
   "source": "base"
  },
  {
   "mod_id": "Intelligence6",
   "affix_type": "Suffix",
   "group": "Intelligence",
   "level": 55,
   "text": [
    "+(25-27) to Intelligence"
   ],
   "weight": 1,
   "source": "base"
  },
  {
   "mod_id": "Intelligence7",
   "affix_type": "Suffix",
   "group": "Intelligence",
   "level": 66,
   "text": [
    "+(28-30) to Intelligence"
   ],
   "weight": 1,
   "source": "base"
  },
  {
   "mod_id": "Intelligence8",
   "affix_type": "Suffix",
   "group": "Intelligence",
   "level": 74,
   "text": [
    "+(31-33) to Intelligence"
   ],
   "weight": 1,
   "source": "base"
  },
  {
   "mod_id": "FireResist1",
   "affix_type": "Suffix",
   "group": "FireResistance",
   "level": 1,
   "text": [
    "+(6-10)% to Fire Resistance"
   ],
   "weight": 1,
   "source": "base"
  },
  {
   "mod_id": "FireResist2",
   "affix_type": "Suffix",
   "group": "FireResistance",
   "level": 12,
   "text": [
    "+(11-15)% to Fire Resistance"
   ],
   "weight": 1,
   "source": "base"
  },
  {
   "mod_id": "FireResist3",
   "affix_type": "Suffix",
   "group": "FireResistance",
   "level": 24,
   "text": [
    "+(16-20)% to Fire Resistance"
   ],
   "weight": 1,
   "source": "base"
  },
  {
   "mod_id": "FireResist4",
   "affix_type": "Suffix",
   "group": "FireResistance",
   "level": 36,
   "text": [
    "+(21-25)% to Fire Resistance"
   ],
   "weight": 1,
   "source": "base"
  },
  {
   "mod_id": "FireResist5",
   "affix_type": "Suffix",
   "group": "FireResistance",
   "level": 48,
   "text": [
    "+(26-30)% to Fire Resistance"
   ],
   "weight": 1,
   "source": "base"
  },
  {
   "mod_id": "FireResist6",
   "affix_type": "Suffix",
   "group": "FireResistance",
   "level": 60,
   "text": [
    "+(31-35)% to Fire Resistance"
   ],
   "weight": 1,
   "source": "base"
  },
  {
   "mod_id": "FireResist7",
   "affix_type": "Suffix",
   "group": "FireResistance",
   "level": 71,
   "text": [
    "+(36-40)% to Fire Resistance"
   ],
   "weight": 1,
   "source": "base"
  },
  {
   "mod_id": "FireResist8",
   "affix_type": "Suffix",
   "group": "FireResistance",
   "level": 82,
   "text": [
    "+(41-45)% to Fire Resistance"
   ],
   "weight": 1,
   "source": "base"
  },
  {
   "mod_id": "ColdResist1",
   "affix_type": "Suffix",
   "group": "ColdResistance",
   "level": 1,
   "text": [
    "+(6-10)% to Cold Resistance"
   ],
   "weight": 1,
   "source": "base"
  },
  {
   "mod_id": "ColdResist2",
   "affix_type": "Suffix",
   "group": "ColdResistance",
   "level": 14,
   "text": [
    "+(11-15)% to Cold Resistance"
   ],
   "weight": 1,
   "source": "base"
  },
  {
   "mod_id": "ColdResist3",
   "affix_type": "Suffix",
   "group": "ColdResistance",
   "level": 26,
   "text": [
    "+(16-20)% to Cold Resistance"
   ],
   "weight": 1,
   "source": "base"
  },
  {
   "mod_id": "ColdResist4",
   "affix_type": "Suffix",
   "group": "ColdResistance",
   "level": 38,
   "text": [
    "+(21-25)% to Cold Resistance"
   ],
   "weight": 1,
   "source": "base"
  },
  {
   "mod_id": "ColdResist5",
   "affix_type": "Suffix",
   "group": "ColdResistance",
   "level": 50,
   "text": [
    "+(26-30)% to Cold Resistance"
   ],
   "weight": 1,
   "source": "base"
  },
  {
   "mod_id": "ColdResist6",
   "affix_type": "Suffix",
   "group": "ColdResistance",
   "level": 60,
   "text": [
    "+(31-35)% to Cold Resistance"
   ],
   "weight": 1,
   "source": "base"
  },
  {
   "mod_id": "ColdResist7",
   "affix_type": "Suffix",
   "group": "ColdResistance",
   "level": 71,
   "text": [
    "+(36-40)% to Cold Resistance"
   ],
   "weight": 1,
   "source": "base"
  },
  {
   "mod_id": "ColdResist8",
   "affix_type": "Suffix",
   "group": "ColdResistance",
   "level": 82,
   "text": [
    "+(41-45)% to Cold Resistance"
   ],
   "weight": 1,
   "source": "base"
  },
  {
   "mod_id": "LightningResist1",
   "affix_type": "Suffix",
   "group": "LightningResistance",
   "level": 1,
   "text": [
    "+(6-10)% to Lightning Resistance"
   ],
   "weight": 1,
   "source": "base"
  },
  {
   "mod_id": "LightningResist2",
   "affix_type": "Suffix",
   "group": "LightningResistance",
   "level": 13,
   "text": [
    "+(11-15)% to Lightning Resistance"
   ],
   "weight": 1,
   "source": "base"
  },
  {
   "mod_id": "LightningResist3",
   "affix_type": "Suffix",
   "group": "LightningResistance",
   "level": 25,
   "text": [
    "+(16-20)% to Lightning Resistance"
   ],
   "weight": 1,
   "source": "base"
  },
  {
   "mod_id": "LightningResist4",
   "affix_type": "Suffix",
   "group": "LightningResistance",
   "level": 37,
   "text": [
    "+(21-25)% to Lightning Resistance"
   ],
   "weight": 1,
   "source": "base"
  },
  {
   "mod_id": "LightningResist5",
   "affix_type": "Suffix",
   "group": "LightningResistance",
   "level": 49,
   "text": [
    "+(26-30)% to Lightning Resistance"
   ],
   "weight": 1,
   "source": "base"
  },
  {
   "mod_id": "LightningResist6",
   "affix_type": "Suffix",
   "group": "LightningResistance",
   "level": 60,
   "text": [
    "+(31-35)% to Lightning Resistance"
   ],
   "weight": 1,
   "source": "base"
  },
  {
   "mod_id": "LightningResist7",
   "affix_type": "Suffix",
   "group": "LightningResistance",
   "level": 71,
   "text": [
    "+(36-40)% to Lightning Resistance"
   ],
   "weight": 1,
   "source": "base"
  },
  {
   "mod_id": "LightningResist8",
   "affix_type": "Suffix",
   "group": "LightningResistance",
   "level": 82,
   "text": [
    "+(41-45)% to Lightning Resistance"
   ],
   "weight": 1,
   "source": "base"
  },
  {
   "mod_id": "ChaosResist1",
   "affix_type": "Suffix",
   "group": "ChaosResistance",
   "level": 16,
   "text": [
    "+(4-7)% to Chaos Resistance"
   ],
   "weight": 1,
   "source": "base"
  },
  {
   "mod_id": "ChaosResist2",
   "affix_type": "Suffix",
   "group": "ChaosResistance",
   "level": 30,
   "text": [
    "+(8-11)% to Chaos Resistance"
   ],
   "weight": 1,
   "source": "base"
  },
  {
   "mod_id": "ChaosResist3",
   "affix_type": "Suffix",
   "group": "ChaosResistance",
   "level": 44,
   "text": [
    "+(12-15)% to Chaos Resistance"
   ],
   "weight": 1,
   "source": "base"
  },
  {
   "mod_id": "ChaosResist4",
   "affix_type": "Suffix",
   "group": "ChaosResistance",
   "level": 56,
   "text": [
    "+(16-19)% to Chaos Resistance"
   ],
   "weight": 1,
   "source": "base"
  },
  {
   "mod_id": "ChaosResist5",
   "affix_type": "Suffix",
   "group": "ChaosResistance",
   "level": 68,
   "text": [
    "+(20-23)% to Chaos Resistance"
   ],
   "weight": 1,
   "source": "base"
  },
  {
   "mod_id": "ChaosResist6",
   "affix_type": "Suffix",
   "group": "ChaosResistance",
   "level": 81,
   "text": [
    "+(24-27)% to Chaos Resistance"
   ],
   "weight": 1,
   "source": "base"
  },
  {
   "mod_id": "IncreasedLife1",
   "affix_type": "Prefix",
   "group": "IncreasedLife",
   "level": 1,
   "text": [
    "+(10-19) to maximum Life"
   ],
   "weight": 1,
   "source": "base"
  },
  {
   "mod_id": "IncreasedLife2",
   "affix_type": "Prefix",
   "group": "IncreasedLife",
   "level": 6,
   "text": [
    "+(20-29) to maximum Life"
   ],
   "weight": 1,
   "source": "base"
  },
  {
   "mod_id": "IncreasedLife3",
   "affix_type": "Prefix",
   "group": "IncreasedLife",
   "level": 16,
   "text": [
    "+(30-39) to maximum Life"
   ],
   "weight": 1,
   "source": "base"
  },
  {
   "mod_id": "IncreasedLife4",
   "affix_type": "Prefix",
   "group": "IncreasedLife",
   "level": 24,
   "text": [
    "+(40-59) to maximum Life"
   ],
   "weight": 1,
   "source": "base"
  },
  {
   "mod_id": "IncreasedLife5",
   "affix_type": "Prefix",
   "group": "IncreasedLife",
   "level": 33,
   "text": [
    "+(60-69) to maximum Life"
   ],
   "weight": 1,
   "source": "base"
  },
  {
   "mod_id": "IncreasedLife6",
   "affix_type": "Prefix",
   "group": "IncreasedLife",
   "level": 38,
   "text": [
    "+(70-84) to maximum Life"
   ],
   "weight": 1,
   "source": "base"
  },
  {
   "mod_id": "IncreasedLife7",
   "affix_type": "Prefix",
   "group": "IncreasedLife",
   "level": 46,
   "text": [
    "+(85-99) to maximum Life"
   ],
   "weight": 1,
   "source": "base"
  },
  {
   "mod_id": "IncreasedLife8",
   "affix_type": "Prefix",
   "group": "IncreasedLife",
   "level": 54,
   "text": [
    "+(100-119) to maximum Life"
   ],
   "weight": 1,
   "source": "base"
  },
  {
   "mod_id": "IncreasedLife9",
   "affix_type": "Prefix",
   "group": "IncreasedLife",
   "level": 60,
   "text": [
    "+(120-149) to maximum Life"
   ],
   "weight": 1,
   "source": "base"
  },
  {
   "mod_id": "IncreasedMana1",
   "affix_type": "Prefix",
   "group": "IncreasedMana",
   "level": 1,
   "text": [
    "+(10-14) to maximum Mana"
   ],
   "weight": 1,
   "source": "base"
  },
  {
   "mod_id": "IncreasedMana2",
   "affix_type": "Prefix",
   "group": "IncreasedMana",
   "level": 6,
   "text": [
    "+(15-24) to maximum Mana"
   ],
   "weight": 1,
   "source": "base"
  },
  {
   "mod_id": "IncreasedMana3",
   "affix_type": "Prefix",
   "group": "IncreasedMana",
   "level": 16,
   "text": [
    "+(25-34) to maximum Mana"
   ],
   "weight": 1,
   "source": "base"
  },
  {
   "mod_id": "IncreasedMana4",
   "affix_type": "Prefix",
   "group": "IncreasedMana",
   "level": 25,
   "text": [
    "+(35-54) to maximum Mana"
   ],
   "weight": 1,
   "source": "base"
  },
  {
   "mod_id": "IncreasedMana5",
   "affix_type": "Prefix",
   "group": "IncreasedMana",
   "level": 33,
   "text": [
    "+(55-64) to maximum Mana"
   ],
   "weight": 1,
   "source": "base"
  },
  {
   "mod_id": "IncreasedMana6",
   "affix_type": "Prefix",
   "group": "IncreasedMana",
   "level": 38,
   "text": [
    "+(65-79) to maximum Mana"
   ],
   "weight": 1,
   "source": "base"
  },
  {
   "mod_id": "IncreasedMana7",
   "affix_type": "Prefix",
   "group": "IncreasedMana",
   "level": 46,
   "text": [
    "+(80-89) to maximum Mana"
   ],
   "weight": 1,
   "source": "base"
  },
  {
   "mod_id": "IncreasedMana8",
   "affix_type": "Prefix",
   "group": "IncreasedMana",
   "level": 54,
   "text": [
    "+(90-104) to maximum Mana"
   ],
   "weight": 1,
   "source": "base"
  },
  {
   "mod_id": "IncreasedMana9",
   "affix_type": "Prefix",
   "group": "IncreasedMana",
   "level": 60,
   "text": [
    "+(105-124) to maximum Mana"
   ],
   "weight": 1,
   "source": "base"
  },
  {
   "mod_id": "LocalIncreasedPhysicalDamageReductionRating1",
   "affix_type": "Prefix",
   "group": "LocalPhysicalDamageReductionRating",
   "level": 1,
   "text": [
    "+(16-27) to Armour"
   ],
   "weight": 1,
   "source": "base"
  },
  {
   "mod_id": "LocalIncreasedPhysicalDamageReductionRating2",
   "affix_type": "Prefix",
   "group": "LocalPhysicalDamageReductionRating",
   "level": 8,
   "text": [
    "+(28-56) to Armour"
   ],
   "weight": 1,
   "source": "base"
  },
  {
   "mod_id": "LocalIncreasedPhysicalDamageReductionRating3",
   "affix_type": "Prefix",
   "group": "LocalPhysicalDamageReductionRating",
   "level": 16,
   "text": [
    "+(57-77) to Armour"
   ],
   "weight": 1,
   "source": "base"
  },
  {
   "mod_id": "LocalIncreasedPhysicalDamageReductionRating4",
   "affix_type": "Prefix",
   "group": "LocalPhysicalDamageReductionRating",
   "level": 25,
   "text": [
    "+(78-98) to Armour"
   ],
   "weight": 1,
   "source": "base"
  },
  {
   "mod_id": "LocalIncreasedPhysicalDamageReductionRating5",
   "affix_type": "Prefix",
   "group": "LocalPhysicalDamageReductionRating",
   "level": 33,
   "text": [
    "+(99-127) to Armour"
   ],
   "weight": 1,
   "source": "base"
  },
  {
   "mod_id": "LocalIncreasedPhysicalDamageReductionRating6",
   "affix_type": "Prefix",
   "group": "LocalPhysicalDamageReductionRating",
   "level": 46,
   "text": [
    "+(128-159) to Armour"
   ],
   "weight": 1,
   "source": "base"
  },
  {
   "mod_id": "LocalIncreasedPhysicalDamageReductionRating7__",
   "affix_type": "Prefix",
   "group": "LocalPhysicalDamageReductionRating",
   "level": 54,
   "text": [
    "+(160-190) to Armour"
   ],
   "weight": 1,
   "source": "base"
  },
  {
   "mod_id": "LocalIncreasedPhysicalDamageReductionRating8",
   "affix_type": "Prefix",
   "group": "LocalPhysicalDamageReductionRating",
   "level": 60,
   "text": [
    "+(191-221) to Armour"
   ],
   "weight": 1,
   "source": "base"
  },
  {
   "mod_id": "LocalIncreasedPhysicalDamageReductionRating9_",
   "affix_type": "Prefix",
   "group": "LocalPhysicalDamageReductionRating",
   "level": 65,
   "text": [
    "+(222-248) to Armour"
   ],
   "weight": 1,
   "source": "base"
  },
  {
   "mod_id": "LocalIncreasedPhysicalDamageReductionRating10",
   "affix_type": "Prefix",
   "group": "LocalPhysicalDamageReductionRating",
   "level": 75,
   "text": [
    "+(249-277) to Armour"
   ],
   "weight": 1,
   "source": "base"
  },
  {
   "mod_id": "LocalIncreasedPhysicalDamageReductionRating11",
   "affix_type": "Prefix",
   "group": "LocalPhysicalDamageReductionRating",
   "level": 79,
   "text": [
    "+(278-310) to Armour"
   ],
   "weight": 1,
   "source": "base"
  },
  {
   "mod_id": "LocalIncreasedEvasionRating1",
   "affix_type": "Prefix",
   "group": "LocalEvasionRating",
   "level": 1,
   "text": [
    "+(11-18) to Evasion Rating"
   ],
   "weight": 1,
   "source": "base"
  },
  {
   "mod_id": "LocalIncreasedEvasionRating2",
   "affix_type": "Prefix",
   "group": "LocalEvasionRating",
   "level": 8,
   "text": [
    "+(19-46) to Evasion Rating"
   ],
   "weight": 1,
   "source": "base"
  },
  {
   "mod_id": "LocalIncreasedEvasionRating3",
   "affix_type": "Prefix",
   "group": "LocalEvasionRating",
   "level": 16,
   "text": [
    "+(47-66) to Evasion Rating"
   ],
   "weight": 1,
   "source": "base"
  },
  {
   "mod_id": "LocalIncreasedEvasionRating4",
   "affix_type": "Prefix",
   "group": "LocalEvasionRating",
   "level": 25,
   "text": [
    "+(67-87) to Evasion Rating"
   ],
   "weight": 1,
   "source": "base"
  },
  {
   "mod_id": "LocalIncreasedEvasionRating5",
   "affix_type": "Prefix",
   "group": "LocalEvasionRating",
   "level": 33,
   "text": [
    "+(88-116) to Evasion Rating"
   ],
   "weight": 1,
   "source": "base"
  },
  {
   "mod_id": "LocalIncreasedEvasionRating6",
   "affix_type": "Prefix",
   "group": "LocalEvasionRating",
   "level": 46,
   "text": [
    "+(117-146) to Evasion Rating"
   ],
   "weight": 1,
   "source": "base"
  },
  {
   "mod_id": "LocalIncreasedEvasionRating7_",
   "affix_type": "Prefix",
   "group": "LocalEvasionRating",
   "level": 54,
   "text": [
    "+(147-176) to Evasion Rating"
   ],
   "weight": 1,
   "source": "base"
  },
  {
   "mod_id": "LocalIncreasedEvasionRating8",
   "affix_type": "Prefix",
   "group": "LocalEvasionRating",
   "level": 60,
   "text": [
    "+(177-207) to Evasion Rating"
   ],
   "weight": 1,
   "source": "base"
  },
  {
   "mod_id": "LocalIncreasedEvasionRating9___",
   "affix_type": "Prefix",
   "group": "LocalEvasionRating",
   "level": 65,
   "text": [
    "+(208-234) to Evasion Rating"
   ],
   "weight": 1,
   "source": "base"
  },
  {
   "mod_id": "LocalIncreasedEvasionRating10",
   "affix_type": "Prefix",
   "group": "LocalEvasionRating",
   "level": 75,
   "text": [
    "+(235-261) to Evasion Rating"
   ],
   "weight": 1,
   "source": "base"
  },
  {
   "mod_id": "LocalIncreasedEvasionRating11",
   "affix_type": "Prefix",
   "group": "LocalEvasionRating",
   "level": 79,
   "text": [
    "+(262-300) to Evasion Rating"
   ],
   "weight": 1,
   "source": "base"
  },
  {
   "mod_id": "LocalIncreasedEnergyShield1",
   "affix_type": "Prefix",
   "group": "LocalEnergyShield",
   "level": 1,
   "text": [
    "+(10-17) to maximum Energy Shield"
   ],
   "weight": 1,
   "source": "base"
  },
  {
   "mod_id": "LocalIncreasedEnergyShield2",
   "affix_type": "Prefix",
   "group": "LocalEnergyShield",
   "level": 8,
   "text": [
    "+(18-24) to maximum Energy Shield"
   ],
   "weight": 1,
   "source": "base"
  },
  {
   "mod_id": "LocalIncreasedEnergyShield3",
   "affix_type": "Prefix",
   "group": "LocalEnergyShield",
   "level": 16,
   "text": [
    "+(25-30) to maximum Energy Shield"
   ],
   "weight": 1,
   "source": "base"
  },
  {
   "mod_id": "LocalIncreasedEnergyShield4",
   "affix_type": "Prefix",
   "group": "LocalEnergyShield",
   "level": 25,
   "text": [
    "+(31-35) to maximum Energy Shield"
   ],
   "weight": 1,
   "source": "base"
  },
  {
   "mod_id": "LocalIncreasedEnergyShield5",
   "affix_type": "Prefix",
   "group": "LocalEnergyShield",
   "level": 33,
   "text": [
    "+(36-41) to maximum Energy Shield"
   ],
   "weight": 1,
   "source": "base"
  },
  {
   "mod_id": "LocalIncreasedEnergyShield6",
   "affix_type": "Prefix",
   "group": "LocalEnergyShield",
   "level": 46,
   "text": [
    "+(42-47) to maximum Energy Shield"
   ],
   "weight": 1,
   "source": "base"
  },
  {
   "mod_id": "LocalIncreasedEnergyShield7",
   "affix_type": "Prefix",
   "group": "LocalEnergyShield",
   "level": 54,
   "text": [
    "+(48-60) to maximum Energy Shield"
   ],
   "weight": 1,
   "source": "base"
  },
  {
   "mod_id": "LocalIncreasedEnergyShield8",
   "affix_type": "Prefix",
   "group": "LocalEnergyShield",
   "level": 60,
   "text": [
    "+(61-73) to maximum Energy Shield"
   ],
   "weight": 1,
   "source": "base"
  },
  {
   "mod_id": "LocalIncreasedEnergyShield9",
   "affix_type": "Prefix",
   "group": "LocalEnergyShield",
   "level": 65,
   "text": [
    "+(74-80) to maximum Energy Shield"
   ],
   "weight": 1,
   "source": "base"
  },
  {
   "mod_id": "LocalIncreasedEnergyShield10",
   "affix_type": "Prefix",
   "group": "LocalEnergyShield",
   "level": 70,
   "text": [
    "+(81-90) to maximum Energy Shield"
   ],
   "weight": 1,
   "source": "base"
  },
  {
   "mod_id": "LocalIncreasedEnergyShield11",
   "affix_type": "Prefix",
   "group": "LocalEnergyShield",
   "level": 79,
   "text": [
    "+(91-96) to maximum Energy Shield"
   ],
   "weight": 1,
   "source": "base"
  },
  {
   "mod_id": "LocalBaseArmourAndEvasionRating1",
   "affix_type": "Prefix",
   "group": "LocalBaseArmourAndEvasionRating",
   "level": 1,
   "text": [
    "+(9-16) to Armour",
    "+(6-10) to Evasion Rating"
   ],
   "weight": 1,
   "source": "base"
  },
  {
   "mod_id": "LocalBaseArmourAndEvasionRating2",
   "affix_type": "Prefix",
   "group": "LocalBaseArmourAndEvasionRating",
   "level": 16,
   "text": [
    "+(17-46) to Armour",
    "+(11-41) to Evasion Rating"
   ],
   "weight": 1,
   "source": "base"
  },
  {
   "mod_id": "LocalBaseArmourAndEvasionRating3",
   "affix_type": "Prefix",
   "group": "LocalBaseArmourAndEvasionRating",
   "level": 33,
   "text": [
    "+(47-71) to Armour",
    "+(42-64) to Evasion Rating"
   ],
   "weight": 1,
   "source": "base"
  },
  {
   "mod_id": "LocalBaseArmourAndEvasionRating4",
   "affix_type": "Prefix",
   "group": "LocalBaseArmourAndEvasionRating",
   "level": 46,
   "text": [
    "+(72-85) to Armour",
    "+(65-78) to Evasion Rating"
   ],
   "weight": 1,
   "source": "base"
  },
  {
   "mod_id": "LocalBaseArmourAndEvasionRating5",
   "affix_type": "Prefix",
   "group": "LocalBaseArmourAndEvasionRating",
   "level": 54,
   "text": [
    "+(86-102) to Armour",
    "+(79-94) to Evasion Rating"
   ],
   "weight": 1,
   "source": "base"
  },
  {
   "mod_id": "LocalBaseArmourAndEvasionRating6_",
   "affix_type": "Prefix",
   "group": "LocalBaseArmourAndEvasionRating",
   "level": 60,
   "text": [
    "+(103-127) to Armour",
    "+(95-119) to Evasion Rating"
   ],
   "weight": 1,
   "source": "base"
  },
  {
   "mod_id": "LocalBaseArmourAndEvasionRating7",
   "affix_type": "Prefix",
   "group": "LocalBaseArmourAndEvasionRating",
   "level": 65,
   "text": [
    "+(128-149) to Armour",
    "+(120-141) to Evasion Rating"
   ],
   "weight": 1,
   "source": "base"
  },
  {
   "mod_id": "LocalBaseArmourAndEvasionRating8",
   "affix_type": "Prefix",
   "group": "LocalBaseArmourAndEvasionRating",
   "level": 75,
   "text": [
    "+(150-170) to Armour",
    "+(142-161) to Evasion Rating"
   ],
   "weight": 1,
   "source": "base"
  },
  {
   "mod_id": "LocalBaseArmourAndEnergyShield1",
   "affix_type": "Prefix",
   "group": "LocalBaseArmourAndEnergyShield",
   "level": 1,
   "text": [
    "+(9-16) to Armour",
    "+(5-8) to maximum Energy Shield"
   ],
   "weight": 1,
   "source": "base"
  },
  {
   "mod_id": "LocalBaseArmourAndEnergyShield2_",
   "affix_type": "Prefix",
   "group": "LocalBaseArmourAndEnergyShield",
   "level": 16,
   "text": [
    "+(17-46) to Armour",
    "+(9-15) to maximum Energy Shield"
   ],
   "weight": 1,
   "source": "base"
  },
  {
   "mod_id": "LocalBaseArmourAndEnergyShield3",
   "affix_type": "Prefix",
   "group": "LocalBaseArmourAndEnergyShield",
   "level": 33,
   "text": [
    "+(47-71) to Armour",
    "+(16-21) to maximum Energy Shield"
   ],
   "weight": 1,
   "source": "base"
  },
  {
   "mod_id": "LocalBaseArmourAndEnergyShield4",
   "affix_type": "Prefix",
   "group": "LocalBaseArmourAndEnergyShield",
   "level": 46,
   "text": [
    "+(72-85) to Armour",
    "+(22-25) to maximum Energy Shield"
   ],
   "weight": 1,
   "source": "base"
  },
  {
   "mod_id": "LocalBaseArmourAndEnergyShield5",
   "affix_type": "Prefix",
   "group": "LocalBaseArmourAndEnergyShield",
   "level": 54,
   "text": [
    "+(86-102) to Armour",
    "+(26-29) to maximum Energy Shield"
   ],
   "weight": 1,
   "source": "base"
  },
  {
   "mod_id": "LocalBaseArmourAndEnergyShield6",
   "affix_type": "Prefix",
   "group": "LocalBaseArmourAndEnergyShield",
   "level": 60,
   "text": [
    "+(103-127) to Armour",
    "+(30-36) to maximum Energy Shield"
   ],
   "weight": 1,
   "source": "base"
  },
  {
   "mod_id": "LocalBaseArmourAndEnergyShield7",
   "affix_type": "Prefix",
   "group": "LocalBaseArmourAndEnergyShield",
   "level": 65,
   "text": [
    "+(128-149) to Armour",
    "+(37-42) to maximum Energy Shield"
   ],
   "weight": 1,
   "source": "base"
  },
  {
   "mod_id": "LocalBaseArmourAndEnergyShield8",
   "affix_type": "Prefix",
   "group": "LocalBaseArmourAndEnergyShield",
   "level": 75,
   "text": [
    "+(150-170) to Armour",
    "+(43-48) to maximum Energy Shield"
   ],
   "weight": 1,
   "source": "base"
  },
  {
   "mod_id": "LocalBaseEvasionRatingAndEnergyShield1",
   "affix_type": "Prefix",
   "group": "LocalBaseEvasionRatingAndEnergyShield",
   "level": 1,
   "text": [
    "+(6-10) to Evasion Rating",
    "+(5-8) to maximum Energy Shield"
   ],
   "weight": 1,
   "source": "base"
  },
  {
   "mod_id": "LocalBaseEvasionRatingAndEnergyShield2",
   "affix_type": "Prefix",
   "group": "LocalBaseEvasionRatingAndEnergyShield",
   "level": 16,
   "text": [
    "+(11-41) to Evasion Rating",
    "+(9-15) to maximum Energy Shield"
   ],
   "weight": 1,
   "source": "base"
  },
  {
   "mod_id": "LocalBaseEvasionRatingAndEnergyShield3",
   "affix_type": "Prefix",
   "group": "LocalBaseEvasionRatingAndEnergyShield",
   "level": 33,
   "text": [
    "+(42-64) to Evasion Rating",
    "+(16-21) to maximum Energy Shield"
   ],
   "weight": 1,
   "source": "base"
  },
  {
   "mod_id": "LocalBaseEvasionRatingAndEnergyShield4",
   "affix_type": "Prefix",
   "group": "LocalBaseEvasionRatingAndEnergyShield",
   "level": 46,
   "text": [
    "+(65-78) to Evasion Rating",
    "+(22-25) to maximum Energy Shield"
   ],
   "weight": 1,
   "source": "base"
  },
  {
   "mod_id": "LocalBaseEvasionRatingAndEnergyShield5_",
   "affix_type": "Prefix",
   "group": "LocalBaseEvasionRatingAndEnergyShield",
   "level": 54,
   "text": [
    "+(79-94) to Evasion Rating",
    "+(26-29) to maximum Energy Shield"
   ],
   "weight": 1,
   "source": "base"
  },
  {
   "mod_id": "LocalBaseEvasionRatingAndEnergyShield6",
   "affix_type": "Prefix",
   "group": "LocalBaseEvasionRatingAndEnergyShield",
   "level": 60,
   "text": [
    "+(95-119) to Evasion Rating",
    "+(30-36) to maximum Energy Shield"
   ],
   "weight": 1,
   "source": "base"
  },
  {
   "mod_id": "LocalBaseEvasionRatingAndEnergyShield7___",
   "affix_type": "Prefix",
   "group": "LocalBaseEvasionRatingAndEnergyShield",
   "level": 65,
   "text": [
    "+(120-141) to Evasion Rating",
    "+(37-42) to maximum Energy Shield"
   ],
   "weight": 1,
   "source": "base"
  },
  {
   "mod_id": "LocalBaseEvasionRatingAndEnergyShield8___",
   "affix_type": "Prefix",
   "group": "LocalBaseEvasionRatingAndEnergyShield",
   "level": 75,
   "text": [
    "+(142-161) to Evasion Rating",
    "+(43-48) to maximum Energy Shield"
   ],
   "weight": 1,
   "source": "base"
  },
  {
   "mod_id": "LocalIncreasedArmourAndEvasionAndEnergyShield1",
   "affix_type": "Prefix",
   "group": "LocalArmourAndEvasionAndEnergyShield",
   "level": 2,
   "text": [
    "(15-26)% increased Armour, Evasion and Energy Shield"
   ],
   "weight": 1,
   "source": "base"
  },
  {
   "mod_id": "LocalIncreasedArmourAndEvasionAndEnergyShield2",
   "affix_type": "Prefix",
   "group": "LocalArmourAndEvasionAndEnergyShield",
   "level": 16,
   "text": [
    "(27-42)% increased Armour, Evasion and Energy Shield"
   ],
   "weight": 1,
   "source": "base"
  },
  {
   "mod_id": "LocalIncreasedArmourAndEvasionAndEnergyShield3",
   "affix_type": "Prefix",
   "group": "LocalArmourAndEvasionAndEnergyShield",
   "level": 33,
   "text": [
    "(43-55)% increased Armour, Evasion and Energy Shield"
   ],
   "weight": 1,
   "source": "base"
  },
  {
   "mod_id": "LocalIncreasedArmourAndEvasionAndEnergyShield4",
   "affix_type": "Prefix",
   "group": "LocalArmourAndEvasionAndEnergyShield",
   "level": 46,
   "text": [
    "(56-67)% increased Armour, Evasion and Energy Shield"
   ],
   "weight": 1,
   "source": "base"
  },
  {
   "mod_id": "LocalIncreasedArmourAndEvasionAndEnergyShield5",
   "affix_type": "Prefix",
   "group": "LocalArmourAndEvasionAndEnergyShield",
   "level": 54,
   "text": [
    "(68-79)% increased Armour, Evasion and Energy Shield"
   ],
   "weight": 1,
   "source": "base"
  },
  {
   "mod_id": "LocalIncreasedArmourAndEvasionAndEnergyShield6",
   "affix_type": "Prefix",
   "group": "LocalArmourAndEvasionAndEnergyShield",
   "level": 60,
   "text": [
    "(80-91)% increased Armour, Evasion and Energy Shield"
   ],
   "weight": 1,
   "source": "base"
  },
  {
   "mod_id": "LocalIncreasedArmourAndEvasionAndEnergyShield7",
   "affix_type": "Prefix",
   "group": "LocalArmourAndEvasionAndEnergyShield",
   "level": 65,
   "text": [
    "(92-100)% increased Armour, Evasion and Energy Shield"
   ],
   "weight": 1,
   "source": "base"
  },
  {
   "mod_id": "LocalIncreasedArmourAndEvasionAndEnergyShield8",
   "affix_type": "Prefix",
   "group": "LocalArmourAndEvasionAndEnergyShield",
   "level": 75,
   "text": [
    "(101-110)% increased Armour, Evasion and Energy Shield"
   ],
   "weight": 1,
   "source": "base"
  },
  {
   "mod_id": "ReducedLocalAttributeRequirements1",
   "affix_type": "Suffix",
   "group": "LocalAttributeRequirements",
   "level": 24,
   "text": [
    "15% reduced Attribute Requirements"
   ],
   "weight": 1,
   "source": "base"
  },
  {
   "mod_id": "ReducedLocalAttributeRequirements2",
   "affix_type": "Suffix",
   "group": "LocalAttributeRequirements",
   "level": 32,
   "text": [
    "20% reduced Attribute Requirements"
   ],
   "weight": 1,
   "source": "base"
  },
  {
   "mod_id": "ReducedLocalAttributeRequirements3",
   "affix_type": "Suffix",
   "group": "LocalAttributeRequirements",
   "level": 40,
   "text": [
    "25% reduced Attribute Requirements"
   ],
   "weight": 1,
   "source": "base"
  },
  {
   "mod_id": "ReducedLocalAttributeRequirements4",
   "affix_type": "Suffix",
   "group": "LocalAttributeRequirements",
   "level": 52,
   "text": [
    "30% reduced Attribute Requirements"
   ],
   "weight": 1,
   "source": "base"
  },
  {
   "mod_id": "ReducedLocalAttributeRequirements5",
   "affix_type": "Suffix",
   "group": "LocalAttributeRequirements",
   "level": 60,
   "text": [
    "35% reduced Attribute Requirements"
   ],
   "weight": 1,
   "source": "base"
  },
  {
   "mod_id": "AddedPhysicalDamage1",
   "affix_type": "Prefix",
   "group": "PhysicalDamage",
   "level": 1,
   "text": [
    "Adds (1-2) to 3 Physical Damage to Attacks"
   ],
   "weight": 1,
   "source": "base"
  },
  {
   "mod_id": "AddedPhysicalDamage2",
   "affix_type": "Prefix",
   "group": "PhysicalDamage",
   "level": 8,
   "text": [
    "Adds (2-3) to (4-6) Physical Damage to Attacks"
   ],
   "weight": 1,
   "source": "base"
  },
  {
   "mod_id": "AddedPhysicalDamage3",
   "affix_type": "Prefix",
   "group": "PhysicalDamage",
   "level": 16,
   "text": [
    "Adds (2-4) to (5-8) Physical Damage to Attacks"
   ],
   "weight": 1,
   "source": "base"
  },
  {
   "mod_id": "AddedPhysicalDamage4",
   "affix_type": "Prefix",
   "group": "PhysicalDamage",
   "level": 33,
   "text": [
    "Adds (4-6) to (8-11) Physical Damage to Attacks"
   ],
   "weight": 1,
   "source": "base"
  },
  {
   "mod_id": "AddedPhysicalDamage5",
   "affix_type": "Prefix",
   "group": "PhysicalDamage",
   "level": 46,
   "text": [
    "Adds (5-7) to (9-13) Physical Damage to Attacks"
   ],
   "weight": 1,
   "source": "base"
  },
  {
   "mod_id": "AddedPhysicalDamage6",
   "affix_type": "Prefix",
   "group": "PhysicalDamage",
   "level": 54,
   "text": [
    "Adds (6-10) to (12-17) Physical Damage to Attacks"
   ],
   "weight": 1,
   "source": "base"
  },
  {
   "mod_id": "AddedPhysicalDamage7",
   "affix_type": "Prefix",
   "group": "PhysicalDamage",
   "level": 60,
   "text": [
    "Adds (7-11) to (14-20) Physical Damage to Attacks"
   ],
   "weight": 1,
   "source": "base"
  },
  {
   "mod_id": "AddedPhysicalDamage8",
   "affix_type": "Prefix",
   "group": "PhysicalDamage",
   "level": 65,
   "text": [
    "Adds (10-15) to (18-26) Physical Damage to Attacks"
   ],
   "weight": 1,
   "source": "base"
  },
  {
   "mod_id": "AddedPhysicalDamage9",
   "affix_type": "Prefix",
   "group": "PhysicalDamage",
   "level": 75,
   "text": [
    "Adds (12-19) to (22-32) Physical Damage to Attacks"
   ],
   "weight": 1,
   "source": "base"
  },
  {
   "mod_id": "AddedFireDamage1",
   "affix_type": "Prefix",
   "group": "FireDamage",
   "level": 1,
   "text": [
    "Adds (1-2) to 3 Fire damage to Attacks"
   ],
   "weight": 1,
   "source": "base"
  },
  {
   "mod_id": "AddedFireDamage2",
   "affix_type": "Prefix",
   "group": "FireDamage",
   "level": 8,
   "text": [
    "Adds (3-5) to (6-9) Fire damage to Attacks"
   ],
   "weight": 1,
   "source": "base"
  },
  {
   "mod_id": "AddedFireDamage3",
   "affix_type": "Prefix",
   "group": "FireDamage",
   "level": 16,
   "text": [
    "Adds (6-8) to (10-13) Fire damage to Attacks"
   ],
   "weight": 1,
   "source": "base"
  },
  {
   "mod_id": "AddedFireDamage4",
   "affix_type": "Prefix",
   "group": "FireDamage",
   "level": 33,
   "text": [
    "Adds (9-11) to (14-17) Fire damage to Attacks"
   ],
   "weight": 1,
   "source": "base"
  },
  {
   "mod_id": "AddedFireDamage5",
   "affix_type": "Prefix",
   "group": "FireDamage",
   "level": 46,
   "text": [
    "Adds (12-13) to (18-20) Fire damage to Attacks"
   ],
   "weight": 1,
   "source": "base"
  },
  {
   "mod_id": "AddedFireDamage6",
   "affix_type": "Prefix",
   "group": "FireDamage",
   "level": 54,
   "text": [
    "Adds (11-16) to (21-26) Fire damage to Attacks"
   ],
   "weight": 1,
   "source": "base"
  },
  {
   "mod_id": "AddedFireDamage7",
   "affix_type": "Prefix",
   "group": "FireDamage",
   "level": 60,
   "text": [
    "Adds (13-19) to (27-32) Fire damage to Attacks"
   ],
   "weight": 1,
   "source": "base"
  },
  {
   "mod_id": "AddedFireDamage8",
   "affix_type": "Prefix",
   "group": "FireDamage",
   "level": 65,
   "text": [
    "Adds (20-24) to (33-36) Fire damage to Attacks"
   ],
   "weight": 1,
   "source": "base"
  },
  {
   "mod_id": "AddedFireDamage9",
   "affix_type": "Prefix",
   "group": "FireDamage",
   "level": 75,
   "text": [
    "Adds (25-29) to (37-45) Fire damage to Attacks"
   ],
   "weight": 1,
   "source": "base"
  },
  {
   "mod_id": "AddedColdDamage1",
   "affix_type": "Prefix",
   "group": "ColdDamage",
   "level": 1,
   "text": [
    "Adds 1 to (2-3) Cold damage to Attacks"
   ],
   "weight": 1,
   "source": "base"
  },
  {
   "mod_id": "AddedColdDamage2",
   "affix_type": "Prefix",
   "group": "ColdDamage",
   "level": 8,
   "text": [
    "Adds (3-4) to (5-8) Cold damage to Attacks"
   ],
   "weight": 1,
   "source": "base"
  },
  {
   "mod_id": "AddedColdDamage3",
   "affix_type": "Prefix",
   "group": "ColdDamage",
   "level": 16,
   "text": [
    "Adds (5-6) to (9-11) Cold damage to Attacks"
   ],
   "weight": 1,
   "source": "base"
  },
  {
   "mod_id": "AddedColdDamage4",
   "affix_type": "Prefix",
   "group": "ColdDamage",
   "level": 33,
   "text": [
    "Adds (7-8) to (12-14) Cold damage to Attacks"
   ],
   "weight": 1,
   "source": "base"
  },
  {
   "mod_id": "AddedColdDamage5",
   "affix_type": "Prefix",
   "group": "ColdDamage",
   "level": 46,
   "text": [
    "Adds (9-10) to (15-17) Cold damage to Attacks"
   ],
   "weight": 1,
   "source": "base"
  },
  {
   "mod_id": "AddedColdDamage6",
   "affix_type": "Prefix",
   "group": "ColdDamage",
   "level": 54,
   "text": [
    "Adds (11-13) to (18-21) Cold damage to Attacks"
   ],
   "weight": 1,
   "source": "base"
  },
  {
   "mod_id": "AddedColdDamage7",
   "affix_type": "Prefix",
   "group": "ColdDamage",
   "level": 60,
   "text": [
    "Adds (14-15) to (22-24) Cold damage to Attacks"
   ],
   "weight": 1,
   "source": "base"
  },
  {
   "mod_id": "AddedColdDamage8",
   "affix_type": "Prefix",
   "group": "ColdDamage",
   "level": 65,
   "text": [
    "Adds (16-20) to (25-31) Cold damage to Attacks"
   ],
   "weight": 1,
   "source": "base"
  },
  {
   "mod_id": "AddedColdDamage9",
   "affix_type": "Prefix",
   "group": "ColdDamage",
   "level": 75,
   "text": [
    "Adds (21-24) to (32-37) Cold damage to Attacks"
   ],
   "weight": 1,
   "source": "base"
  },
  {
   "mod_id": "AddedLightningDamage1",
   "affix_type": "Prefix",
   "group": "LightningDamage",
   "level": 1,
   "text": [
    "Adds 1 to (4-6) Lightning damage to Attacks"
   ],
   "weight": 1,
   "source": "base"
  },
  {
   "mod_id": "AddedLightningDamage2",
   "affix_type": "Prefix",
   "group": "LightningDamage",
   "level": 8,
   "text": [
    "Adds 1 to (10-15) Lightning damage to Attacks"
   ],
   "weight": 1,
   "source": "base"
  },
  {
   "mod_id": "AddedLightningDamage3",
   "affix_type": "Prefix",
   "group": "LightningDamage",
   "level": 16,
   "text": [
    "Adds 1 to (16-22) Lightning damage to Attacks"
   ],
   "weight": 1,
   "source": "base"
  },
  {
   "mod_id": "AddedLightningDamage4",
   "affix_type": "Prefix",
   "group": "LightningDamage",
   "level": 33,
   "text": [
    "Adds 1 to (23-27) Lightning damage to Attacks"
   ],
   "weight": 1,
   "source": "base"
  },
  {
   "mod_id": "AddedLightningDamage5",
   "affix_type": "Prefix",
   "group": "LightningDamage",
   "level": 46,
   "text": [
    "Adds 1 to (28-32) Lightning damage to Attacks"
   ],
   "weight": 1,
   "source": "base"
  },
  {
   "mod_id": "AddedLightningDamage6",
   "affix_type": "Prefix",
   "group": "LightningDamage",
   "level": 54,
   "text": [
    "Adds (1-2) to (33-40) Lightning damage to Attacks"
   ],
   "weight": 1,
   "source": "base"
  },
  {
   "mod_id": "AddedLightningDamage7",
   "affix_type": "Prefix",
   "group": "LightningDamage",
   "level": 60,
   "text": [
    "Adds (1-2) to (41-47) Lightning damage to Attacks"
   ],
   "weight": 1,
   "source": "base"
  },
  {
   "mod_id": "AddedLightningDamage8",
   "affix_type": "Prefix",
   "group": "LightningDamage",
   "level": 65,
   "text": [
    "Adds (1-3) to (48-59) Lightning damage to Attacks"
   ],
   "weight": 1,
   "source": "base"
  },
  {
   "mod_id": "AddedLightningDamage9",
   "affix_type": "Prefix",
   "group": "LightningDamage",
   "level": 75,
   "text": [
    "Adds (1-4) to (60-71) Lightning damage to Attacks"
   ],
   "weight": 1,
   "source": "base"
  },
  {
   "mod_id": "GlobalMeleeSkillGemLevel1",
   "affix_type": "Suffix",
   "group": "GlobalIncreaseMeleeSkillGemLevel",
   "level": 5,
   "text": [
    "+1 to Level of all Melee Skills"
   ],
   "weight": 1,
   "source": "base"
  },
  {
   "mod_id": "GlobalMeleeSkillGemLevel2",
   "affix_type": "Suffix",
   "group": "GlobalIncreaseMeleeSkillGemLevel",
   "level": 41,
   "text": [
    "+2 to Level of all Melee Skills"
   ],
   "weight": 1,
   "source": "base"
  },
  {
   "mod_id": "LifeLeech2",
   "affix_type": "Suffix",
   "group": "LifeLeechPermyriad",
   "level": 21,
   "text": [
    "Leech (6-6.9)% of Physical Attack Damage as Life"
   ],
   "weight": 1,
   "source": "base"
  },
  {
   "mod_id": "LifeLeech3",
   "affix_type": "Suffix",
   "group": "LifeLeechPermyriad",
   "level": 38,
   "text": [
    "Leech (7-7.9)% of Physical Attack Damage as Life"
   ],
   "weight": 1,
   "source": "base"
  },
  {
   "mod_id": "LifeLeech4",
   "affix_type": "Suffix",
   "group": "LifeLeechPermyriad",
   "level": 54,
   "text": [
    "Leech (8-8.9)% of Physical Attack Damage as Life"
   ],
   "weight": 1,
   "source": "base"
  },
  {
   "mod_id": "LifeLeech5",
   "affix_type": "Suffix",
   "group": "LifeLeechPermyriad",
   "level": 65,
   "text": [
    "Leech (9-9.9)% of Physical Attack Damage as Life"
   ],
   "weight": 1,
   "source": "base"
  },
  {
   "mod_id": "ManaLeech2",
   "affix_type": "Suffix",
   "group": "ManaLeechPermyriad",
   "level": 21,
   "text": [
    "Leech (5-5.9)% of Physical Attack Damage as Mana"
   ],
   "weight": 1,
   "source": "base"
  },
  {
   "mod_id": "ManaLeech3",
   "affix_type": "Suffix",
   "group": "ManaLeechPermyriad",
   "level": 38,
   "text": [
    "Leech (6-6.9)% of Physical Attack Damage as Mana"
   ],
   "weight": 1,
   "source": "base"
  },
  {
   "mod_id": "ManaLeech4",
   "affix_type": "Suffix",
   "group": "ManaLeechPermyriad",
   "level": 54,
   "text": [
    "Leech (7-7.9)% of Physical Attack Damage as Mana"
   ],
   "weight": 1,
   "source": "base"
  },
  {
   "mod_id": "ManaLeech5",
   "affix_type": "Suffix",
   "group": "ManaLeechPermyriad",
   "level": 65,
   "text": [
    "Leech (8-8.9)% of Physical Attack Damage as Mana"
   ],
   "weight": 1,
   "source": "base"
  },
  {
   "mod_id": "LifeGainedFromEnemyDeath1",
   "affix_type": "Suffix",
   "group": "LifeGainedFromEnemyDeath",
   "level": 1,
   "text": [
    "Gain (4-6) Life per enemy killed"
   ],
   "weight": 1,
   "source": "base"
  },
  {
   "mod_id": "LifeGainedFromEnemyDeath2",
   "affix_type": "Suffix",
   "group": "LifeGainedFromEnemyDeath",
   "level": 11,
   "text": [
    "Gain (7-9) Life per enemy killed"
   ],
   "weight": 1,
   "source": "base"
  },
  {
   "mod_id": "LifeGainedFromEnemyDeath3",
   "affix_type": "Suffix",
   "group": "LifeGainedFromEnemyDeath",
   "level": 22,
   "text": [
    "Gain (10-18) Life per enemy killed"
   ],
   "weight": 1,
   "source": "base"
  },
  {
   "mod_id": "LifeGainedFromEnemyDeath4",
   "affix_type": "Suffix",
   "group": "LifeGainedFromEnemyDeath",
   "level": 33,
   "text": [
    "Gain (19-28) Life per enemy killed"
   ],
   "weight": 1,
   "source": "base"
  },
  {
   "mod_id": "LifeGainedFromEnemyDeath5",
   "affix_type": "Suffix",
   "group": "LifeGainedFromEnemyDeath",
   "level": 44,
   "text": [
    "Gain (29-40) Life per enemy killed"
   ],
   "weight": 1,
   "source": "base"
  },
  {
   "mod_id": "LifeGainedFromEnemyDeath6",
   "affix_type": "Suffix",
   "group": "LifeGainedFromEnemyDeath",
   "level": 55,
   "text": [
    "Gain (41-53) Life per enemy killed"
   ],
   "weight": 1,
   "source": "base"
  },
  {
   "mod_id": "LifeGainedFromEnemyDeath7",
   "affix_type": "Suffix",
   "group": "LifeGainedFromEnemyDeath",
   "level": 66,
   "text": [
    "Gain (54-68) Life per enemy killed"
   ],
   "weight": 1,
   "source": "base"
  },
  {
   "mod_id": "LifeGainedFromEnemyDeath8",
   "affix_type": "Suffix",
   "group": "LifeGainedFromEnemyDeath",
   "level": 77,
   "text": [
    "Gain (69-84) Life per enemy killed"
   ],
   "weight": 1,
   "source": "base"
  },
  {
   "mod_id": "ManaGainedFromEnemyDeath1",
   "affix_type": "Suffix",
   "group": "ManaGainedFromEnemyDeath",
   "level": 1,
   "text": [
    "Gain (2-3) Mana per enemy killed"
   ],
   "weight": 1,
   "source": "base"
  },
  {
   "mod_id": "ManaGainedFromEnemyDeath2",
   "affix_type": "Suffix",
   "group": "ManaGainedFromEnemyDeath",
   "level": 12,
   "text": [
    "Gain (4-5) Mana per enemy killed"
   ],
   "weight": 1,
   "source": "base"
  },
  {
   "mod_id": "ManaGainedFromEnemyDeath3",
   "affix_type": "Suffix",
   "group": "ManaGainedFromEnemyDeath",
   "level": 23,
   "text": [
    "Gain (6-9) Mana per enemy killed"
   ],
   "weight": 1,
   "source": "base"
  },
  {
   "mod_id": "ManaGainedFromEnemyDeath4",
   "affix_type": "Suffix",
   "group": "ManaGainedFromEnemyDeath",
   "level": 34,
   "text": [
    "Gain (10-14) Mana per enemy killed"
   ],
   "weight": 1,
   "source": "base"
  },
  {
   "mod_id": "ManaGainedFromEnemyDeath5",
   "affix_type": "Suffix",
   "group": "ManaGainedFromEnemyDeath",
   "level": 45,
   "text": [
    "Gain (15-20) Mana per enemy killed"
   ],
   "weight": 1,
   "source": "base"
  },
  {
   "mod_id": "ManaGainedFromEnemyDeath6",
   "affix_type": "Suffix",
   "group": "ManaGainedFromEnemyDeath",
   "level": 56,
   "text": [
    "Gain (21-27) Mana per enemy killed"
   ],
   "weight": 1,
   "source": "base"
  },
  {
   "mod_id": "ManaGainedFromEnemyDeath7",
   "affix_type": "Suffix",
   "group": "ManaGainedFromEnemyDeath",
   "level": 67,
   "text": [
    "Gain (28-35) Mana per enemy killed"
   ],
   "weight": 1,
   "source": "base"
  },
  {
   "mod_id": "ManaGainedFromEnemyDeath8",
   "affix_type": "Suffix",
   "group": "ManaGainedFromEnemyDeath",
   "level": 78,
   "text": [
    "Gain (36-45) Mana per enemy killed"
   ],
   "weight": 1,
   "source": "base"
  },
  {
   "mod_id": "LifeGainPerTarget1",
   "affix_type": "Suffix",
   "group": "LifeGainPerTarget",
   "level": 8,
   "text": [
    "Gain 2 Life per Enemy Hit with Attacks"
   ],
   "weight": 1,
   "source": "base"
  },
  {
   "mod_id": "LifeGainPerTarget2",
   "affix_type": "Suffix",
   "group": "LifeGainPerTarget",
   "level": 20,
   "text": [
    "Gain 3 Life per Enemy Hit with Attacks"
   ],
   "weight": 1,
   "source": "base"
  },
  {
   "mod_id": "LifeGainPerTarget3",
   "affix_type": "Suffix",
   "group": "LifeGainPerTarget",
   "level": 30,
   "text": [
    "Gain 4 Life per Enemy Hit with Attacks"
   ],
   "weight": 1,
   "source": "base"
  },
  {
   "mod_id": "LifeGainPerTarget4",
   "affix_type": "Suffix",
   "group": "LifeGainPerTarget",
   "level": 40,
   "text": [
    "Gain 5 Life per Enemy Hit with Attacks"
   ],
   "weight": 1,
   "source": "base"
  },
  {
   "mod_id": "IncreasedAttackSpeed1",
   "affix_type": "Suffix",
   "group": "IncreasedAttackSpeed",
   "level": 1,
   "text": [
    "(5-7)% increased Attack Speed"
   ],
   "weight": 1,
   "source": "base"
  },
  {
   "mod_id": "IncreasedAttackSpeed2",
   "affix_type": "Suffix",
   "group": "IncreasedAttackSpeed",
   "level": 22,
   "text": [
    "(8-10)% increased Attack Speed"
   ],
   "weight": 1,
   "source": "base"
  },
  {
   "mod_id": "IncreasedAttackSpeed3",
   "affix_type": "Suffix",
   "group": "IncreasedAttackSpeed",
   "level": 37,
   "text": [
    "(11-13)% increased Attack Speed"
   ],
   "weight": 1,
   "source": "base"
  },
  {
   "mod_id": "IncreasedAttackSpeed4",
   "affix_type": "Suffix",
   "group": "IncreasedAttackSpeed",
   "level": 60,
   "text": [
    "(14-16)% increased Attack Speed"
   ],
   "weight": 1,
   "source": "base"
  },
  {
   "mod_id": "IncreasedAccuracy1",
   "affix_type": "Prefix",
   "group": "IncreasedAccuracy",
   "level": 1,
   "text": [
    "+(11-32) to Accuracy Rating"
   ],
   "weight": 1,
   "source": "base"
  },
  {
   "mod_id": "IncreasedAccuracy2",
   "affix_type": "Prefix",
   "group": "IncreasedAccuracy",
   "level": 11,
   "text": [
    "+(33-60) to Accuracy Rating"
   ],
   "weight": 1,
   "source": "base"
  },
  {
   "mod_id": "IncreasedAccuracy3",
   "affix_type": "Prefix",
   "group": "IncreasedAccuracy",
   "level": 18,
   "text": [
    "+(61-84) to Accuracy Rating"
   ],
   "weight": 1,
   "source": "base"
  },
  {
   "mod_id": "IncreasedAccuracy4",
   "affix_type": "Prefix",
   "group": "IncreasedAccuracy",
   "level": 26,
   "text": [
    "+(85-123) to Accuracy Rating"
   ],
   "weight": 1,
   "source": "base"
  },
  {
   "mod_id": "IncreasedAccuracy5",
   "affix_type": "Prefix",
   "group": "IncreasedAccuracy",
   "level": 36,
   "text": [
    "+(124-167) to Accuracy Rating"
   ],
   "weight": 1,
   "source": "base"
  },
  {
   "mod_id": "IncreasedAccuracy6",
   "affix_type": "Prefix",
   "group": "IncreasedAccuracy",
   "level": 48,
   "text": [
    "+(168-236) to Accuracy Rating"
   ],
   "weight": 1,
   "source": "base"
  },
  {
   "mod_id": "IncreasedAccuracy7",
   "affix_type": "Prefix",
   "group": "IncreasedAccuracy",
   "level": 58,
   "text": [
    "+(237-346) to Accuracy Rating"
   ],
   "weight": 1,
   "source": "base"
  },
  {
   "mod_id": "IncreasedAccuracy8",
   "affix_type": "Prefix",
   "group": "IncreasedAccuracy",
   "level": 67,
   "text": [
    "+(347-450) to Accuracy Rating"
   ],
   "weight": 1,
   "source": "base"
  },
  {
   "mod_id": "IncreasedAccuracy9",
   "affix_type": "Prefix",
   "group": "IncreasedAccuracy",
   "level": 76,
   "text": [
    "+(451-550) to Accuracy Rating"
   ],
   "weight": 1,
   "source": "base"
  },
  {
   "mod_id": "CriticalMultiplier1",
   "affix_type": "Suffix",
   "group": "CriticalStrikeMultiplier",
   "level": 8,
   "text": [
    "(10-14)% increased Critical Damage Bonus"
   ],
   "weight": 1,
   "source": "base"
  },
  {
   "mod_id": "CriticalMultiplier2",
   "affix_type": "Suffix",
   "group": "CriticalStrikeMultiplier",
   "level": 21,
   "text": [
    "(15-19)% increased Critical Damage Bonus"
   ],
   "weight": 1,
   "source": "base"
  },
  {
   "mod_id": "CriticalMultiplier3",
   "affix_type": "Suffix",
   "group": "CriticalStrikeMultiplier",
   "level": 31,
   "text": [
    "(20-24)% increased Critical Damage Bonus"
   ],
   "weight": 1,
   "source": "base"
  },
  {
   "mod_id": "CriticalMultiplier4",
   "affix_type": "Suffix",
   "group": "CriticalStrikeMultiplier",
   "level": 45,
   "text": [
    "(25-29)% increased Critical Damage Bonus"
   ],
   "weight": 1,
   "source": "base"
  },
  {
   "mod_id": "CriticalMultiplier5",
   "affix_type": "Suffix",
   "group": "CriticalStrikeMultiplier",
   "level": 59,
   "text": [
    "(30-34)% increased Critical Damage Bonus"
   ],
   "weight": 1,
   "source": "base"
  },
  {
   "mod_id": "ItemFoundRarityIncrease1",
   "affix_type": "Suffix",
   "group": "ItemFoundRarityIncrease",
   "level": 3,
   "text": [
    "(6-10)% increased Rarity of Items found"
   ],
   "weight": 1,
   "source": "base"
  },
  {
   "mod_id": "ItemFoundRarityIncrease2",
   "affix_type": "Suffix",
   "group": "ItemFoundRarityIncrease",
   "level": 24,
   "text": [
    "(11-14)% increased Rarity of Items found"
   ],
   "weight": 1,
   "source": "base"
  },
  {
   "mod_id": "ItemFoundRarityIncrease3",
   "affix_type": "Suffix",
   "group": "ItemFoundRarityIncrease",
   "level": 40,
   "text": [
    "(15-18)% increased Rarity of Items found"
   ],
   "weight": 1,
   "source": "base"
  },
  {
   "mod_id": "EnergyShieldRechargeRate4",
   "affix_type": "Suffix",
   "group": "EnergyShieldRegeneration",
   "level": 48,
   "text": [
    "(16-19)% increased Energy Shield Recharge Rate"
   ],
   "weight": 1,
   "source": "base"
  },
  {
   "mod_id": "EnergyShieldRechargeRate5______",
   "affix_type": "Suffix",
   "group": "EnergyShieldRegeneration",
   "level": 66,
   "text": [
    "(20-23)% increased Energy Shield Recharge Rate"
   ],
   "weight": 1,
   "source": "base"
  },
  {
   "mod_id": "EnergyShieldRechargeRate6",
   "affix_type": "Suffix",
   "group": "EnergyShieldRegeneration",
   "level": 81,
   "text": [
    "(24-27)% increased Energy Shield Recharge Rate"
   ],
   "weight": 1,
   "source": "base"
  },
  {
   "mod_id": "ArmourAppliesToElementalDamage1",
   "affix_type": "Suffix",
   "group": "ArmourAppliesToElementalDamage",
   "level": 1,
   "text": [
    "+(14-19)% of Armour also applies to Elemental Damage"
   ],
   "weight": 1,
   "source": "base"
  },
  {
   "mod_id": "ArmourAppliesToElementalDamage2",
   "affix_type": "Suffix",
   "group": "ArmourAppliesToElementalDamage",
   "level": 16,
   "text": [
    "+(20-25)% of Armour also applies to Elemental Damage"
   ],
   "weight": 1,
   "source": "base"
  },
  {
   "mod_id": "ArmourAppliesToElementalDamage3",
   "affix_type": "Suffix",
   "group": "ArmourAppliesToElementalDamage",
   "level": 36,
   "text": [
    "+(26-31)% of Armour also applies to Elemental Damage"
   ],
   "weight": 1,
   "source": "base"
  },
  {
   "mod_id": "ArmourAppliesToElementalDamage4",
   "affix_type": "Suffix",
   "group": "ArmourAppliesToElementalDamage",
   "level": 48,
   "text": [
    "+(32-37)% of Armour also applies to Elemental Damage"
   ],
   "weight": 1,
   "source": "base"
  },
  {
   "mod_id": "ArmourAppliesToElementalDamage5",
   "affix_type": "Suffix",
   "group": "ArmourAppliesToElementalDamage",
   "level": 66,
   "text": [
    "+(38-43)% of Armour also applies to Elemental Damage"
   ],
   "weight": 1,
   "source": "base"
  },
  {
   "mod_id": "ArmourAppliesToElementalDamage6",
   "affix_type": "Suffix",
   "group": "ArmourAppliesToElementalDamage",
   "level": 81,
   "text": [
    "+(44-50)% of Armour also applies to Elemental Damage"
   ],
   "weight": 1,
   "source": "base"
  },
  {
   "mod_id": "EvasionGrantsDeflection1",
   "affix_type": "Suffix",
   "group": "EvasionAppliesToDeflection",
   "level": 1,
   "text": [
    "Gain Deflection Rating equal to (8-11)% of Evasion Rating"
   ],
   "weight": 1,
   "source": "base"
  },
  {
   "mod_id": "EvasionGrantsDeflection2",
   "affix_type": "Suffix",
   "group": "EvasionAppliesToDeflection",
   "level": 16,
   "text": [
    "Gain Deflection Rating equal to (12-14)% of Evasion Rating"
   ],
   "weight": 1,
   "source": "base"
  },
  {
   "mod_id": "EvasionGrantsDeflection3",
   "affix_type": "Suffix",
   "group": "EvasionAppliesToDeflection",
   "level": 36,
   "text": [
    "Gain Deflection Rating equal to (15-17)% of Evasion Rating"
   ],
   "weight": 1,
   "source": "base"
  },
  {
   "mod_id": "EvasionGrantsDeflection4",
   "affix_type": "Suffix",
   "group": "EvasionAppliesToDeflection",
   "level": 48,
   "text": [
    "Gain Deflection Rating equal to (18-20)% of Evasion Rating"
   ],
   "weight": 1,
   "source": "base"
  },
  {
   "mod_id": "EvasionGrantsDeflection5",
   "affix_type": "Suffix",
   "group": "EvasionAppliesToDeflection",
   "level": 66,
   "text": [
    "Gain Deflection Rating equal to (21-23)% of Evasion Rating"
   ],
   "weight": 1,
   "source": "base"
  },
  {
   "mod_id": "EvasionGrantsDeflection6",
   "affix_type": "Suffix",
   "group": "EvasionAppliesToDeflection",
   "level": 81,
   "text": [
    "Gain Deflection Rating equal to (24-26)% of Evasion Rating"
   ],
   "weight": 1,
   "source": "base"
  },
  {
   "mod_id": "EssenceLightningRecoupLife1",
   "affix_type": "Suffix",
   "group": "EssenceLightningRecoupLife",
   "level": 72,
   "text": [
    "(26-30)% of Lightning Damage taken Recouped as Life"
   ],
   "weight": 0,
   "source": "essence_only"
  },
  {
   "mod_id": "EssenceGoldDropped1",
   "affix_type": "Suffix",
   "group": "EssenceGoldDropped",
   "level": 72,
   "text": [
    "(10-15)% increased Quantity of Gold Dropped by Slain Enemies"
   ],
   "weight": 0,
   "source": "essence_only"
  }
 ]
}